Metadata-Version: 1.2
Name: telegaden
Version: 0.0.2
Summary: Python Telegram TDLib sync client
Home-page: https://github.com/Yakuden/telega
Author: Yakuden
Author-email: yakudenn@gmail.com
License: MIT
Keywords: telegram telega client tglib
Platform: UNKNOWN
Requires-Python: >=3.5
